{"accounts": ["xw5jbes44fvv", "betdicetasks", "wallet.bg", "bluebetbulls", "zcai1ormqlrb", "zmlleebcbihs", "zachreynolds", "yaoerlingyao", "miner.bg", "offer.bg", "wukongmarket", "newdexpublic", "spin..dice", "eossanguodiv", "eosplaybrand", "dice.bg", "felixeosgame", "felixtokenio", "youtube12345", "yucengyu5555", "sportbet1bet", "zxq154451154", "bulls.bg"], "times": [1596506725, 1596506726, 1596506727, 1596506728, 1596506729, 1596506730, 1596506731, 1596506732, 1596506733, 1596506734, 1596506735, 1596506738, 1596506739, 1596506740, 1596506741, 1596506749, 1596506750, 1596506751, 1596506752, 1596506753], "Tx": [[], [14, 19], [], [8, 9], [], [1, 12], [], [5, 16], [], [4, 16, 17], [], [10, 11], [2, 15, 22], [0, 11], [2, 22], [6, 20], [18, 22], [13, 21], [3, 7], [2, 15]], "hedges": {"2020-08-04 10:05:25": ["xw5jbes44fvv", "newdexpublic"], "2020-08-04 10:05:26": ["eosplaybrand", "yucengyu5555"], "2020-08-04 10:05:27": ["zmlleebcbihs", "felixeosgame"], "2020-08-04 10:05:28": ["offer.bg", "miner.bg"], "2020-08-04 10:05:29": ["zmlleebcbihs", "felixeosgame"], "2020-08-04 10:05:30": ["betdicetasks", "spin..dice"], "2020-08-04 10:05:31": ["wukongmarket", "newdexpublic"], "2020-08-04 10:05:32": ["zmlleebcbihs", "felixeosgame"], "2020-08-04 10:05:33": ["wukongmarket", "newdexpublic"], "2020-08-04 10:05:34": ["zcai1ormqlrb", "felixeosgame", "felixtokenio"], "2020-08-04 10:05:35": ["bulls.bg", "wallet.bg", "dice.bg"], "2020-08-04 10:05:38": ["wukongmarket", "newdexpublic"], "2020-08-04 10:05:39": ["bulls.bg", "wallet.bg", "dice.bg"], "2020-08-04 10:05:40": ["xw5jbes44fvv", "newdexpublic"], "2020-08-04 10:05:41": ["bulls.bg", "wallet.bg"], "2020-08-04 10:05:49": ["sportbet1bet", "zachreynolds"], "2020-08-04 10:05:50": ["bulls.bg", "youtube12345"], "2020-08-04 10:05:51": ["zxq154451154", "eossanguodiv"], "2020-08-04 10:05:52": ["yaoerlingyao", "bluebetbulls"], "2020-08-04 10:05:53": ["wallet.bg", "dice.bg"]}}